cythonsendevent/LICENSE
cythonsendevent/README.MD
cythonsendevent/__init__.py
cythonsendevent/cysend.pyx
cythonsendevent/cysend_compile.py
cythonsendevent/requirements.txt
cythonsendevent/thirdparty.json
cythonsendevent-0.11.dist-info/LICENSE.rst
cythonsendevent-0.11.dist-info/METADATA
cythonsendevent-0.11.dist-info/WHEEL
cythonsendevent-0.11.dist-info/top_level.txt
cythonsendevent-0.11.dist-info/RECORD
