Metadata-Version: 2.1
Name: cythonsendevent
Version: 0.11
Summary: Sendevent - Android with Cython
Home-page: https://github.com/hansalemaos/cythonsendevent
Author: Johannes Fischer
Author-email: aulasparticularesdealemaosp@gmail.com
License: MIT
Keywords: Android,Sendevent
Classifier: Development Status :: 4 - Beta
Classifier: Programming Language :: Python :: 3 :: Only
Classifier: Programming Language :: Python :: 3.10
Classifier: Topic :: Software Development :: Libraries :: Python Modules
Classifier: Topic :: Utilities
License-File: LICENSE.rst
Requires-Dist: Cython
Requires-Dist: exceptdrucker
Requires-Dist: numpy
Requires-Dist: regex
Requires-Dist: setuptools
